pygformula/__init__.py
pygformula/comparisons.py
pygformula/data.py
pygformula/interventions.py
pygformula/plot.py
pygformula/version.py
pygformula/parametric_gformula/__init__.py
pygformula/parametric_gformula/bootstrap.py
pygformula/parametric_gformula/fit.py
pygformula/parametric_gformula/histories.py
pygformula/parametric_gformula/parametric_gformula.py
pygformula/parametric_gformula/simulate.py
pygformula/utils/__init__.py
pygformula/utils/helper.py
pygformula/utils/util.py
pygformula-1.1.8.dist-info/licenses/LICENSE
pygformula-1.1.8.dist-info/METADATA
pygformula-1.1.8.dist-info/WHEEL
pygformula-1.1.8.dist-info/top_level.txt
pygformula-1.1.8.dist-info/RECORD
