Metadata-Version: 2.4
Name: pygformula
Version: 1.1.8
Summary: A python implementation of the parametric g-formula
Maintainer: Jing Li
Maintainer-email: jing_li@hsph.harvard.edu
Requires-Python: >=3.8
License-File: LICENSE
Requires-Dist: joblib>=1.2
Requires-Dist: lifelines>=0.27
Requires-Dist: matplotlib>=3.5
Requires-Dist: numpy>=1.22
Requires-Dist: pandas>=1.5
Requires-Dist: prettytable>=3.10
Requires-Dist: pytruncreg>=0.1
Requires-Dist: scipy>=1.10
Requires-Dist: seaborn>=0.11
Requires-Dist: statsmodels>=0.14
Requires-Dist: tqdm>=4.64
Requires-Dist: PyQt5>=5.15
Dynamic: description
Dynamic: description-content-type
Dynamic: license-file
Dynamic: maintainer
Dynamic: maintainer-email
Dynamic: requires-dist
Dynamic: requires-python
Dynamic: summary
